{"slug":"3rq7MXZCow0","lang":"en","author":"Whisper AI + translated by deepl","subtitles":[{"id":1,"startTime":0,"endTime":3.74,"text":"Now, we've heard a lot about you so far, Sakura-san. "},{"id":2,"startTime":3.74,"endTime":6,"text":"Are you okay? Aren't you tired?"},{"id":3,"startTime":6,"endTime":7.56,"text":"Oh, I'm totally fine."},{"id":4,"startTime":7.56,"endTime":10.9,"text":"But you know what, Yakan-kun, we've been talking all day too."},{"id":5,"startTime":10.9,"endTime":12.4,"text":"Aren't you tired?"},{"id":6,"startTime":12.4,"endTime":14.7,"text":"It was fun, though."},{"id":7,"startTime":14.7,"endTime":18.7,"text":"Oh, I just got some really cute snacks."},{"id":8,"startTime":18.7,"endTime":19.9,"text":"Would you like to eat it with me? Here."},{"id":9,"startTime":19.9,"endTime":21.2,"text":"Oh, I like Halloween candy."},{"id":10,"startTime":21.2,"endTime":23.4,"text":"Yes! It's so cute!"},{"id":11,"startTime":23.4,"endTime":26.2,"text":"I want some."},{"id":12,"startTime":26.9,"endTime":28.2,"text":"I love it!"},{"id":13,"startTime":29.304,"endTime":33.304,"text":"I'll go trick-or-treating!"},{"id":14,"startTime":33.304,"endTime":36.304,"text":"I'm Honoka Akimoto from Team Orca!"},{"id":15,"startTime":36.304,"endTime":38.304,"text":"Yes, yes!"},{"id":16,"startTime":38.304,"endTime":39.304,"text":"Yes!"},{"id":17,"startTime":39.304,"endTime":40.304,"text":"I see."},{"id":18,"startTime":40.304,"endTime":41.304,"text":"I see."},{"id":19,"startTime":41.304,"endTime":45.304,"text":"I was just thinking how close you are to Yakkan."},{"id":20,"startTime":45.304,"endTime":46.304,"text":"You thought he was close?"},{"id":21,"startTime":46.304,"endTime":50.304,"text":"Yeah. I was wondering how I knew all that."},{"id":22,"startTime":50.304,"endTime":51.304,"text":"You were?"},{"id":23,"startTime":51.304,"endTime":52.304,"text":"It was you."},{"id":24,"startTime":52.304,"endTime":53.304,"text":"It was me."},{"id":25,"startTime":53.304,"endTime":54.304,"text":"I see."},{"id":26,"startTime":54.304,"endTime":55.304,"text":"It's Halloween."},{"id":27,"startTime":55.304,"endTime":57.304,"text":"Of course I'd say I'm a fan of Akimoto Honoka."},{"id":28,"startTime":58.304,"endTime":59.304,"text":"Aww... Ehhhhh..."},{"id":29,"startTime":59.304,"endTime":60.304,"text":"Ha-ha-ha-ha"},{"id":30,"startTime":60.304,"endTime":61.304,"text":"Ehhhhhh..."},{"id":31,"startTime":61.304,"endTime":62.304,"text":"Hmmm..."},{"id":32,"startTime":62.304,"endTime":66.304,"text":"Let's talk about the future of Team Orca from here!"},{"id":33,"startTime":66.304,"endTime":67.304,"text":"Ooooooo..."},{"id":34,"startTime":67.304,"endTime":72.304,"text":"Well, you know, there are only two months left in this year."},{"id":35,"startTime":72.304,"endTime":74.304,"text":"Well, we've got a lot of things on our schedule, don't we?"},{"id":36,"startTime":74.304,"endTime":79.304,"text":"Well, Shachi will be going on a live house tour starting in December."},{"id":37,"startTime":79.304,"endTime":80.304,"text":"Yes!"},{"id":38,"startTime":80.304,"endTime":83.304,"text":"Yes, from 2023 to 2024."},{"id":39,"startTime":83.304,"endTime":89.304,"text":"We'll be performing at Christmas and New Year's, and also near New Year's."},{"id":40,"startTime":89.304,"endTime":93.304,"text":"So we'll be performing 30 shows in 15 cities across the country."},{"id":41,"startTime":93.304,"endTime":94.304,"text":"That's a lot of excitement, isn't it?"},{"id":42,"startTime":94.304,"endTime":96.304,"text":"Yes, we're going on a live house tour."},{"id":43,"startTime":96.304,"endTime":99.304,"text":"The title of the live tour has been announced, right?"},{"id":44,"startTime":99.304,"endTime":100.304,"text":"That's right!"},{"id":45,"startTime":100.304,"endTime":105.304,"text":"It's called \"Live Spectacle: Life is Short, Let it Blossom."},{"id":46,"startTime":105.304,"endTime":106.304,"text":"Ohhh..."},{"id":47,"startTime":106.304,"endTime":107.304,"text":"I'm so excited!"},{"id":48,"startTime":108.304,"endTime":112.304,"text":"But \"Live Spectacle\" is also one of the points."},{"id":49,"startTime":112.304,"endTime":116.304,"text":"I think you can enjoy various kinds of orcas in this live performance."},{"id":50,"startTime":116.304,"endTime":118.304,"text":"Please come and see us!"},{"id":51,"startTime":118.304,"endTime":119.304,"text":"Please come and see us!"},{"id":52,"startTime":119.304,"endTime":125.304,"text":"And this live house tour is a tour with the full album!"},{"id":53,"startTime":125.304,"endTime":128.304,"text":"The first full album this winter, right?"},{"id":54,"startTime":128.304,"endTime":130.304,"text":"Since you became Wacky Records?"},{"id":55,"startTime":130.304,"endTime":131.304,"text":"That's right. Yes, it is."},{"id":56,"startTime":131.304,"endTime":133.304,"text":"This is our first full-length album."},{"id":57,"startTime":133.304,"endTime":134.304,"text":"Yes, we're releasing it."},{"id":58,"startTime":134.304,"endTime":135.304,"text":"Yes!"},{"id":59,"startTime":136.304,"endTime":139.304,"text":"Yes, we are in the middle of recording."},{"id":60,"startTime":139.304,"endTime":144.304,"text":"We have a lot of recording to do after this."},{"id":61,"startTime":144.304,"endTime":145.304,"text":"That's right."},{"id":62,"startTime":145.304,"endTime":149.304,"text":"There are so many different genres of songs."},{"id":63,"startTime":149.304,"endTime":152.304,"text":"The expression when you sing is different."},{"id":64,"startTime":152.304,"endTime":154.304,"text":"I'm going to sing with a smile on my face."},{"id":65,"startTime":155.304,"endTime":157.304,"text":"I'll go sing with a smile."},{"id":66,"startTime":157.304,"endTime":158.304,"text":"What about you?"},{"id":67,"startTime":158.304,"endTime":159.304,"text":"I'm going to..."},{"id":68,"startTime":161.304,"endTime":162.304,"text":"What's with your shoulder?"},{"id":69,"startTime":163.304,"endTime":164.304,"text":"I'm singing like that."},{"id":70,"startTime":164.304,"endTime":166.304,"text":"You're probably right."},{"id":71,"startTime":166.304,"endTime":168.304,"text":"I'll probably end up like this live."},{"id":72,"startTime":169.304,"endTime":172.304,"text":"And I'm about to turn 26!"},{"id":73,"startTime":172.304,"endTime":173.304,"text":"Happy birthday!"},{"id":74,"startTime":173.304,"endTime":174.304,"text":"Yes!"},{"id":75,"startTime":174.304,"endTime":175.304,"text":"Twenty-six!"},{"id":76,"startTime":175.304,"endTime":177.304,"text":"That's a surprise, isn't it?"},{"id":77,"startTime":177.304,"endTime":182.304,"text":"I didn't think I'd be able to do this activity until I'm 26."},{"id":78,"startTime":182.304,"endTime":184.304,"text":"That's what makes me happy."},{"id":79,"startTime":184.304,"endTime":191.304,"text":"I'm grateful to be in an environment where so many people support me even at my age, but I'm also very happy to be able to do this."},{"id":80,"startTime":191.304,"endTime":199.304,"text":"I will be celebrating my 26th birthday on November 19 at Nagoya Diamond Hall."},{"id":81,"startTime":199.304,"endTime":201.304,"text":"Please come and visit me there too!"},{"id":82,"startTime":201.304,"endTime":202.304,"text":"Yay! Yay!"},{"id":83,"startTime":202.304,"endTime":203.304,"text":"Please, please, please."},{"id":84,"startTime":203.304,"endTime":204.304,"text":"What are you doing?"},{"id":85,"startTime":205.304,"endTime":209.304,"text":"I'm going to try something I've never tried before."},{"id":86,"startTime":210.304,"endTime":212.304,"text":"What do you call me?"},{"id":87,"startTime":212.304,"endTime":214.304,"text":"I'm doing a live show."},{"id":88,"startTime":214.304,"endTime":215.304,"text":"In the live performance?"},{"id":89,"startTime":215.304,"endTime":216.304,"text":"If it were you..."},{"id":90,"startTime":216.304,"endTime":220.304,"text":"You sing the chorus with a voice like a punch in the face"},{"id":91,"startTime":222.304,"endTime":223.304,"text":"Like a punch in the face."},{"id":92,"startTime":223.304,"endTime":224.304,"text":"You sing a lot of choruses, don't you?"},{"id":93,"startTime":224.304,"endTime":225.304,"text":"That's right."},{"id":94,"startTime":225.304,"endTime":227.304,"text":"You do talk a lot, don't you, Mahou-san?"},{"id":95,"startTime":227.304,"endTime":228.304,"text":"During live performances."},{"id":96,"startTime":228.304,"endTime":230.304,"text":"You do a lot of talking."},{"id":97,"startTime":230.304,"endTime":231.304,"text":"Talking?"},{"id":98,"startTime":231.304,"endTime":232.304,"text":"Talking."},{"id":99,"startTime":232.304,"endTime":233.304,"text":"Lines?"},{"id":100,"startTime":233.304,"endTime":234.304,"text":"Thank you for the lines."},{"id":101,"startTime":234.304,"endTime":235.304,"text":"I was thinking of doing a little bit of that."},{"id":102,"startTime":236.304,"endTime":239.304,"text":"I'm thinking of doing a little bit of everything."},{"id":103,"startTime":240.304,"endTime":244.304,"text":"I'm 26 years old and this is the first time I'm doing this."},{"id":104,"startTime":244.304,"endTime":246.304,"text":"You've got a lot on your plate, don't you?"},{"id":105,"startTime":246.304,"endTime":247.304,"text":"That's right."},{"id":106,"startTime":247.304,"endTime":250.304,"text":"If I were to list all the parts I've done so far"},{"id":107,"startTime":250.304,"endTime":252.304,"text":"There's no end to it."},{"id":108,"startTime":252.304,"endTime":255.304,"text":"Almost all the songs we've done so far."},{"id":109,"startTime":255.304,"endTime":257.304,"text":"Singles, title songs...You know, singles, title songs... "},{"id":110,"startTime":257.304,"endTime":259.304,"text":"That's why there are dialogue parts in them."},{"id":111,"startTime":259.304,"endTime":261.304,"text":"I can't keep track."},{"id":112,"startTime":263.304,"endTime":265.304,"text":"I wonder how many lines there are."},{"id":113,"startTime":265.304,"endTime":269.304,"text":"I'm hoping that people will enjoy it."},{"id":114,"startTime":271.304,"endTime":272.304,"text":"It was fun."},{"id":115,"startTime":272.304,"endTime":273.304,"text":"It was fun."},{"id":116,"startTime":273.304,"endTime":274.304,"text":"How was it? I..."},{"id":117,"startTime":275.304,"endTime":276.304,"text":"As a kettle?"},{"id":118,"startTime":276.304,"endTime":278.304,"text":"I don't know..."},{"id":119,"startTime":278.304,"endTime":281.304,"text":"I'm a kettlebug, too, so before I knew it..."},{"id":120,"startTime":282.304,"endTime":284.304,"text":"I might have been a little too familiar."},{"id":121,"startTime":285.304,"endTime":287.304,"text":"You're right."},{"id":122,"startTime":287.304,"endTime":288.304,"text":"That's right."},{"id":123,"startTime":288.304,"endTime":290.304,"text":"You're always talking like a normal kettle of fish."},{"id":124,"startTime":290.304,"endTime":293.304,"text":"I'm not conscious of using honorifics."},{"id":125,"startTime":293.304,"endTime":296.304,"text":"I don't think we've ever spoken that close together."},{"id":126,"startTime":296.304,"endTime":298.304,"text":"So you were easy to talk to, is that right?"},{"id":127,"startTime":298.304,"endTime":299.304,"text":"That's what I'm talking about."},{"id":128,"startTime":299.304,"endTime":301.304,"text":"Yay!"},{"id":129,"startTime":302.304,"endTime":306.304,"text":"I think this is the first time you played the role of kettle boy."},{"id":130,"startTime":306.304,"endTime":307.304,"text":"How did you like it?"},{"id":131,"startTime":307.304,"endTime":310.304,"text":"When I got the offer, I thought"},{"id":132,"startTime":310.304,"endTime":314.304,"text":"I was almost crushed by the pressure of being the 4th kettle kettle"},{"id":133,"startTime":314.304,"endTime":317.304,"text":"I was almost crushed by the pressure of being the 4th kettle."},{"id":134,"startTime":317.304,"endTime":320.304,"text":"But I decided to do my best in the role of the kettle"},{"id":135,"startTime":320.304,"endTime":323.304,"text":"I tried my best to put my heart into the role of the kettle that I have been connecting with."},{"id":136,"startTime":323.304,"endTime":328.304,"text":"As a result, I was able to bring out my own version of the kettle.As a result of my efforts, I was able to create a kettle of my own."},{"id":137,"startTime":328.304,"endTime":330.304,"text":"I felt a sense of accomplishment."},{"id":138,"startTime":330.304,"endTime":332.304,"text":"Well, I hope I'll be invited again."},{"id":139,"startTime":332.304,"endTime":335.304,"text":"I'd like to use the 4th generation this time."},{"id":140,"startTime":335.304,"endTime":336.304,"text":"That's right."},{"id":141,"startTime":336.304,"endTime":339.304,"text":"I'm always looking forward to working with the fourth generation."},{"id":142,"startTime":341.304,"endTime":343.304,"text":"And so, up to this point, I've had the pleasure of working with"},{"id":143,"startTime":343.304,"endTime":344.304,"text":"Honoka Akimoto, the team president"},{"id":144,"startTime":344.304,"endTime":346.304,"text":"and Nao Sakura."},{"id":145,"startTime":346.304,"endTime":348.304,"text":"Bye bye!"}]}